Metadata-Version: 1.0
Name: deckglplotly
Version: 0.0.4
Summary: Deck.gl to Dash Plotly
Home-page: UNKNOWN
Author: joao carabetta
Author-email: UNKNOWN
License: MIT
Platform: UNKNOWN
